exploit.py
testt_abc-99.0.1.dist-info/METADATA
testt_abc-99.0.1.dist-info/WHEEL
testt_abc-99.0.1.dist-info/top_level.txt
testt_abc-99.0.1.dist-info/RECORD
