Metadata-Version: 2.4
Name: testt-abc
Version: 99.0.1
Summary: package for testing dependency confusion
Author: test
License: MIT
Dynamic: author
Dynamic: license
Dynamic: summary
